{"task":[{"id":"10021","status":"new","date":"","project":"","category":"","title":"","plan_h":"0","plan_m":"0","spent_m":"","start":"","end":""},{"id":"10006","status":"working","date":"2022-02-15 00:00:00","project":"","category":"","title":"bbbb","plan_h":"1","plan_m":"60","spent_m":"","start":"00:36","end":""},{"id":"10007","status":"working","date":"2022-02-15 00:00:00","project":"","category":"","title":"count","plan_h":"0","plan_m":"0","spent_m":"","start":"23:16","end":""},{"id":"10019","status":"working","date":"2022-02-19 00:00:00","project":"","category":"","title":"cccccc","plan_h":"0","plan_m":"0","spent_m":"","start":"00:50","end":""},{"id":"10000","status":"00:46","date":"2022-02-20 00:00:00","project":"","category":"","title":"bbbbbbbbbbbbbbbbbbbbbb","plan_h":"1","plan_m":"60","spent_m":"","start":"00:46","end":"00:47"},{"id":"10001","status":"pending","date":"2022-02-13 00:00:00","project":"are","category":"sore","title":"bbb","plan_h":"","plan_m":"","spent_m":"","start":"00:49","end":"01:13","header":"are.sore"},{"id":"10003","status":"pending","date":"2022-02-15 00:00:00","project":"are","category":"sore","title":"bbb","plan_h":"","plan_m":"","spent_m":"","start":"00:49","end":"01:13","header":"are.sore"},{"id":"10011","status":"pending","date":"2022-02-19 00:00:00","project":"are","category":"sore","title":"bbb","plan_h":"","plan_m":"","spent_m":"","start":"00:49","end":"01:13","header":"are.sore"},{"id":"10012","status":"pending","date":"2022-02-19 00:00:00","project":"are","category":"sore","title":"bbb","plan_h":"","plan_m":"","spent_m":"","start":"00:49","end":"01:13","header":"are.sore"},{"id":"10013","status":"pending","date":"2022-02-19 00:00:00","project":"are","category":"sore","title":"bbb","plan_h":"","plan_m":"","spent_m":"","start":"00:49","end":"01:13","header":"are.sore"},{"id":"10014","status":"pending","date":"2022-02-19 00:00:00","project":"are","category":"sore","title":"bbb","plan_h":"","plan_m":"","spent_m":"","start":"00:49","end":"01:13","header":"are.sore"},{"id":"10015","status":"pending","date":"2022-02-19 00:00:00","project":"are","category":"sore","title":"bbb","plan_h":"","plan_m":"","spent_m":"","start":"00:49","end":"01:13","header":"are.sore"},{"id":10002,"status":"done","date":"2022-02-14 00:00:00","project":"are","category":"sore","title":"bbb","plan_h":"","plan_m":"","spent_m":3,"start":"22:23","end":"22:26"},{"id":10004,"status":"done","date":"2022-02-15 00:00:00","project":"are","category":"sore","title":"aあああああああ","plan_h":"","plan_m":"","spent_m":1340,"start":"00:49","end":"23:09"},{"id":10005,"status":"done","date":"2022-02-15 00:00:00","project":"","category":"","title":"test","plan_h":"0","plan_m":"0","spent_m":1343,"start":"00:46","end":"23:09"},{"id":10008,"status":"done","date":"2022-02-19 00:00:00","project":"","category":"","title":"ee","plan_h":"","plan_m":"","spent_m":0,"start":"00:30","end":"00:30"},{"id":10009,"status":"done","date":"2022-02-19 00:00:00","project":"","category":"","title":"aaa","plan_h":"0","plan_m":"0","spent_m":0,"start":"00:32","end":"00:32"},{"id":10010,"status":"done","date":"2022-02-19 00:00:00","project":"","category":"","title":"ccc","plan_h":"0","plan_m":"0","spent_m":4,"start":"00:30","end":"00:34"},{"id":10016,"status":"done","date":"2022-02-19 00:00:00","project":"","category":"","title":"aa","plan_h":"","plan_m":"","spent_m":0,"start":"01:14","end":"01:14"},{"id":10017,"status":"done","date":"2022-02-19 00:00:00","project":"","category":"","title":"ああああ","plan_h":"0","plan_m":"0","spent_m":1309,"start":"00:34","end":"22:23"},{"id":10018,"status":"done","date":"2022-02-19 00:00:00","project":"ares","category":"sore","title":"dd","plan_h":"","plan_m":"","spent_m":0,"start":"23:50","end":"23:50"}],"memo":"bbbbbb\naaa"}